openscoring/__init__.py
openscoring/common.py
openscoring/metadata.py
openscoring/util.py
openscoring-0.8.0.post1.dist-info/licenses/LICENSE.txt
openscoring-0.8.0.post1.dist-info/METADATA
openscoring-0.8.0.post1.dist-info/WHEEL
openscoring-0.8.0.post1.dist-info/top_level.txt
openscoring-0.8.0.post1.dist-info/RECORD
