Metadata-Version: 2.4
Name: openscoring
Version: 0.8.0.post1
Summary: Python client library for the Openscoring REST web service (https://github.com/openscoring/openscoring)
Home-page: https://github.com/openscoring/openscoring-python
Download-URL: https://github.com/openscoring/openscoring-python/archive/0.8.0.post1.tar.gz
Author: Villu Ruusmann
Author-email: villu.ruusmann@gmail.com
License: GNU Affero General Public License (AGPL) version 3.0
Classifier: Development Status :: 5 - Production/Stable
Classifier: Operating System :: OS Independent
Classifier: Programming Language :: Python
Classifier: Intended Audience :: Developers
Classifier: Intended Audience :: Science/Research
Classifier: Topic :: Software Development
Classifier: Topic :: Scientific/Engineering
License-File: LICENSE.txt
Requires-Dist: pandas
Requires-Dist: requests>=2.10.0
Dynamic: author
Dynamic: author-email
Dynamic: classifier
Dynamic: download-url
Dynamic: home-page
Dynamic: license
Dynamic: license-file
Dynamic: requires-dist
Dynamic: summary
